{"students":[{"admission":"admission","reasonAdmission":"reasonAdmission","previousIllness":"previousIllness","medicalHistory":"medicalHistory","privateHospital":"privateHospital","vision":"vision","hearing":"hearing","bloodSugar":"hearing","hbLevel":"hbLevel","bloodGroup":"A+","urineChemistry":"urineChemistry","onTreatment":"Yes","anyObservation":"AOB","studentFit":"Yes","familyDoctor":{"name":"elvo","address":"Nakuru","phone":"0791328653"},"id":"StudentID","surname":"surname","firstName":"firstName","lastName":"lastName","phone":"phone","email":"email","gender":"gender","maritalStatus":"maritalStatus","nationality":"nationality","religion":"religion","nextOfKin":{"name":"Oj","address":"Nakuru","phone":"0791328653"}},{"admission":"admission","reasonAdmission":"reasonAdmission","previousIllness":"previousIllness","medicalHistory":"medicalHistory","privateHospital":"privateHospital","vision":"vision","hearing":"hearing","bloodSugar":"hearing","hbLevel":"hbLevel","bloodGroup":"A+","urineChemistry":"urineChemistry","onTreatment":"Yes","anyObservation":"AOB","studentFit":"Yes","familyDoctor":{"name":"elvo","address":"Nakuru","phone":"0791328653"},"id":"StudentID","surname":"surname","firstName":"firstName","lastName":"lastName","phone":"phone","email":"email","gender":"gender","maritalStatus":"maritalStatus","nationality":"nationality","religion":"religion","nextOfKin":{"name":"Oj","address":"Nakuru","phone":"0791328653"}},{"admission":"admission","reasonAdmission":"reasonAdmission","previousIllness":"previousIllness","medicalHistory":"medicalHistory","privateHospital":"privateHospital","vision":"vision","hearing":"hearing","bloodSugar":"hearing","hbLevel":"hbLevel","bloodGroup":"A+","urineChemistry":"urineChemistry","onTreatment":"Yes","anyObservation":"AOB","studentFit":"Yes","familyDoctor":{"name":"elvo","address":"Nakuru","phone":"0791328653"},"id":"StudentID","surname":"surname","firstName":"firstName","lastName":"lastName","phone":"phone","email":"email","gender":"gender","maritalStatus":"maritalStatus","nationality":"nationality","religion":"religion","nextOfKin":{"name":"Oj","address":"Nakuru","phone":"0791328653"}},{"admission":"admission","reasonAdmission":"reasonAdmission","previousIllness":"previousIllness","medicalHistory":"medicalHistory","privateHospital":"privateHospital","vision":"vision","hearing":"hearing","bloodSugar":"hearing","hbLevel":"hbLevel","bloodGroup":"A+","urineChemistry":"urineChemistry","onTreatment":"Yes","anyObservation":"AOB","studentFit":"Yes","familyDoctor":{"name":"elvo","address":"Nakuru","phone":"0791328653"},"id":"StudentID","surname":"surname","firstName":"firstName","lastName":"lastName","phone":"phone","email":"email","gender":"gender","maritalStatus":"maritalStatus","nationality":"nationality","religion":"religion","nextOfKin":{"name":"Oj","address":"Nakuru","phone":"0791328653"}},{"admission":"admission","reasonAdmission":"reasonAdmission","previousIllness":"previousIllness","medicalHistory":"medicalHistory","privateHospital":"privateHospital","vision":"vision","hearing":"hearing","bloodSugar":"hearing","hbLevel":"hbLevel","bloodGroup":"A+","urineChemistry":"urineChemistry","onTreatment":"Yes","anyObservation":"AOB","studentFit":"Yes","familyDoctor":{"name":"elvo","address":"Nakuru","phone":"0791328653"},"id":"StudentID","surname":"surname","firstName":"firstName","lastName":"lastName","phone":"phone","email":"email","gender":"gender","maritalStatus":"maritalStatus","nationality":"nationality","religion":"religion","nextOfKin":{"name":"Oj","address":"Nakuru","phone":"0791328653"}},{"admission":"admission","reasonAdmission":"reasonAdmission","previousIllness":"previousIllness","medicalHistory":"medicalHistory","privateHospital":"privateHospital","vision":"vision","hearing":"hearing","bloodSugar":"hearing","hbLevel":"hbLevel","bloodGroup":"A+","urineChemistry":"urineChemistry","onTreatment":"Yes","anyObservation":"AOB","studentFit":"Yes","familyDoctor":{"name":"elvo","address":"Nakuru","phone":"0791328653"},"id":"StudentID","surname":"surname","firstName":"firstName","lastName":"lastName","phone":"phone","email":"email","gender":"gender","maritalStatus":"maritalStatus","nationality":"nationality","religion":"religion","nextOfKin":{"name":"Oj","address":"Nakuru","phone":"0791328653"}},{"admission":"admission","reasonAdmission":"reasonAdmission","previousIllness":"previousIllness","medicalHistory":"medicalHistory","privateHospital":"privateHospital","vision":"vision","hearing":"hearing","bloodSugar":"hearing","hbLevel":"hbLevel","bloodGroup":"A+","urineChemistry":"urineChemistry","onTreatment":"Yes","anyObservation":"AOB","studentFit":"Yes","familyDoctor":{"name":"elvo","address":"Nakuru","phone":"0791328653"},"id":"StudentID","surname":"surname","firstName":"firstName","lastName":"lastName","phone":"phone","email":"email","gender":"gender","maritalStatus":"maritalStatus","nationality":"nationality","religion":"religion","nextOfKin":{"name":"Oj","address":"Nakuru","phone":"0791328653"}},{"admission":"admission","reasonAdmission":"reasonAdmission","previousIllness":"previousIllness","medicalHistory":"medicalHistory","privateHospital":"privateHospital","vision":"vision","hearing":"hearing","bloodSugar":"hearing","hbLevel":"hbLevel","bloodGroup":"A+","urineChemistry":"urineChemistry","onTreatment":"Yes","anyObservation":"AOB","studentFit":"Yes","familyDoctor":{"name":"elvo","address":"Nakuru","phone":"0791328653"},"id":"StudentID","surname":"surname","firstName":"firstName","lastName":"lastName","phone":"phone","email":"email","gender":"gender","maritalStatus":"maritalStatus","nationality":"nationality","religion":"religion","nextOfKin":{"name":"Oj","address":"Nakuru","phone":"0791328653"}},{"admission":"admission","reasonAdmission":"reasonAdmission","previousIllness":"previousIllness","medicalHistory":"medicalHistory","privateHospital":"privateHospital","vision":"vision","hearing":"hearing","bloodSugar":"hearing","hbLevel":"hbLevel","bloodGroup":"A+","urineChemistry":"urineChemistry","onTreatment":"Yes","anyObservation":"AOB","studentFit":"Yes","familyDoctor":{"name":"elvo","address":"Nakuru","phone":"0791328653"},"id":"StudentID","surname":"surname","firstName":"firstName","lastName":"lastName","phone":"phone","email":"email","gender":"gender","maritalStatus":"maritalStatus","nationality":"nationality","religion":"religion","nextOfKin":{"name":"Oj","address":"Nakuru","phone":"0791328653"}},{"admission":"admission","reasonAdmission":"reasonAdmission","previousIllness":"previousIllness","medicalHistory":"medicalHistory","privateHospital":"privateHospital","vision":"vision","hearing":"hearing","bloodSugar":"hearing","hbLevel":"hbLevel","bloodGroup":"A+","urineChemistry":"urineChemistry","onTreatment":"Yes","anyObservation":"AOB","studentFit":"Yes","familyDoctor":{"name":"elvo","address":"Nakuru","phone":"0791328653"},"id":"StudentID","surname":"surname","firstName":"firstName","lastName":"lastName","phone":"phone","email":"email","gender":"gender","maritalStatus":"maritalStatus","nationality":"nationality","religion":"religion","nextOfKin":{"name":"Oj","address":"Nakuru","phone":"0791328653"}},{"admission":"admission","reasonAdmission":"reasonAdmission","previousIllness":"previousIllness","medicalHistory":"medicalHistory","privateHospital":"privateHospital","vision":"vision","hearing":"hearing","bloodSugar":"hearing","hbLevel":"hbLevel","bloodGroup":"A+","urineChemistry":"urineChemistry","onTreatment":"Yes","anyObservation":"AOB","studentFit":"Yes","familyDoctor":{"name":"elvo","address":"Nakuru","phone":"0791328653"},"id":"StudentID","surname":"surname","firstName":"firstName","lastName":"lastName","phone":"phone","email":"email","gender":"gender","maritalStatus":"maritalStatus","nationality":"nationality","religion":"religion","nextOfKin":{"name":"Oj","address":"Nakuru","phone":"0791328653"}},{"admission":"admission","reasonAdmission":"reasonAdmission","previousIllness":"previousIllness","medicalHistory":"medicalHistory","privateHospital":"privateHospital","vision":"vision","hearing":"hearing","bloodSugar":"hearing","hbLevel":"hbLevel","bloodGroup":"A+","urineChemistry":"urineChemistry","onTreatment":"Yes","anyObservation":"AOB","studentFit":"Yes","familyDoctor":{"name":"elvo","address":"Nakuru","phone":"0791328653"},"id":"StudentID","surname":"surname","firstName":"firstName","lastName":"lastName","phone":"phone","email":"email","gender":"gender","maritalStatus":"maritalStatus","nationality":"nationality","religion":"religion","nextOfKin":{"name":"Oj","address":"Nakuru","phone":"0791328653"}}]}